find_words_from_file/__init__.py
find_words_from_file/find_words_from_file.py
find_words_from_file-0.0.0.14.dist-info/METADATA
find_words_from_file-0.0.0.14.dist-info/WHEEL
find_words_from_file-0.0.0.14.dist-info/top_level.txt
find_words_from_file-0.0.0.14.dist-info/RECORD
