Metadata-Version: 2.1
Name: find-words-from-file
Version: 0.0.0.14
Summary: input words from file and save output file
Home-page: UNKNOWN
Author: HanByulLee
License: MIT
Platform: UNKNOWN
Requires-Python: >=3
Requires-Dist: pandas
